ymlmaster/__init__.py
ymlmaster/generate_schema.py
ymlmaster/main.py
ymlmaster-0.0.3.1.dist-info/LICENSE
ymlmaster-0.0.3.1.dist-info/METADATA
ymlmaster-0.0.3.1.dist-info/WHEEL
ymlmaster-0.0.3.1.dist-info/entry_points.txt
ymlmaster-0.0.3.1.dist-info/RECORD
